simple_carla/__init__.py
simple_carla/plugin_dialog.py
simple_carla/qt.py
simple_carla/scripts/__init__.py
simple_carla/scripts/sc_plugin_def.py
simple_carla/scripts/sc_plugin_info.py
simple_carla-2.7.0.dist-info/entry_points.txt
simple_carla-2.7.0.dist-info/LICENSE
simple_carla-2.7.0.dist-info/WHEEL
simple_carla-2.7.0.dist-info/METADATA
simple_carla-2.7.0.dist-info/RECORD
