Metadata-Version: 2.1
Name: simple_carla
Version: 2.7.0
Summary: An easy-to-use, object-oriented interface to the carla plugin host.
Author-email: Leon Dionne <ldionne@dridesign.sh.cn>
Classifier: License :: OSI Approved :: GNU General Public License v3 or later (GPLv3+)
Requires-Dist: numpy
Requires-Dist: log_soso
Requires-Dist: PyQt5
Project-URL: Home, https://github.com/Zen-Master-SoSo/simple_carla
